orgora-0.1.2.dist-info/METADATA
orgora-0.1.2.dist-info/WHEEL
orgora/__init__.py
orgora/orgora.cpython-311-x86_64-linux-gnu.so
orgora-0.1.2.dist-info/RECORD
