Metadata-Version: 2.3
Name: orgora
Version: 0.1.2
Classifier: Programming Language :: Rust
Classifier: Programming Language :: Python :: Implementation :: CPython
Classifier: Programming Language :: Python :: Implementation :: PyPy
Summary: org mode peg parser
Requires-Python: >=3.9
Project-URL: Homepage, https://github.com/codegod100/orgorapython
